CalcOge/Calc.py
CalcOge/__init__.py
calcoge-0.0.6.dist-info/METADATA
calcoge-0.0.6.dist-info/WHEEL
calcoge-0.0.6.dist-info/top_level.txt
calcoge-0.0.6.dist-info/RECORD
