Metadata-Version: 2.4
Name: CalcOge
Version: 0.0.6
Summary: Simple calculation of OGE tasks
Home-page: https://github.com/Scholoch/oge-calc.git
Author: Scholoch
Author-email: alf.201105@gmail.com
Project-URL: GitHub, https://github.com/Scholoch
Keywords: oge calc
Classifier: Programming Language :: Python :: 3.13
Classifier: License :: OSI Approved :: MIT License
Classifier: Operating System :: OS Independent
Requires-Python: >=3.6
Dynamic: author
Dynamic: author-email
Dynamic: classifier
Dynamic: description
Dynamic: description-content-type
Dynamic: home-page
Dynamic: keywords
Dynamic: project-url
Dynamic: requires-python
Dynamic: summary
